{"nodes": [{"id": "clerk_ref_clerk_provider", "label": "Clerk Provider Integration Guide", "file_type": "document", "source_file": ".agents/skills/convex-setup-auth/references/clerk.md", "source_location": null, "source_url": null, "captured_at": null, "author": null, "contributor": null}, {"id": "clerk_ref_convex_provider_with_clerk", "label": "ConvexProviderWithClerk Wrapper", "file_type": "concept", "source_file": ".agents/skills/convex-setup-auth/references/clerk.md", "source_location": null, "source_url": null, "captured_at": null, "author": null, "contributor": null}, {"id": "clerk_ref_clerk_auth_config", "label": "convex/auth.config.ts for Clerk", "file_type": "concept", "source_file": ".agents/skills/convex-setup-auth/references/clerk.md", "source_location": null, "source_url": null, "captured_at": null, "author": null, "contributor": null}, {"id": "clerk_ref_use_convex_auth", "label": "useConvexAuth Hook", "file_type": "concept", "source_file": ".agents/skills/convex-setup-auth/references/clerk.md", "source_location": null, "source_url": null, "captured_at": null, "author": null, "contributor": null}, {"id": "convex_auth_pattern_jwt_validation", "label": "Convex JWT Validation Pattern for Third-Party Auth", "file_type": "rationale", "source_file": ".agents/skills/convex-setup-auth/references/clerk.md", "source_location": null, "source_url": null, "captured_at": null, "author": null, "contributor": null}], "edges": [{"source": "clerk_ref_clerk_provider", "target": "clerk_ref_convex_provider_with_clerk", "relation": "references", "confidence": "EXTRACTED", "confidence_score": 1.0, "source_file": ".agents/skills/convex-setup-auth/references/clerk.md", "source_location": "Key Setup Areas", "weight": 1.0}, {"source": "clerk_ref_clerk_provider", "target": "clerk_ref_clerk_auth_config", "relation": "references", "confidence": "EXTRACTED", "confidence_score": 1.0, "source_file": ".agents/skills/convex-setup-auth/references/clerk.md", "source_location": "Key Setup Areas", "weight": 1.0}, {"source": "clerk_ref_clerk_provider", "target": "clerk_ref_use_convex_auth", "relation": "references", "confidence": "EXTRACTED", "confidence_score": 1.0, "source_file": ".agents/skills/convex-setup-auth/references/clerk.md", "source_location": "Gotchas", "weight": 1.0}, {"source": "clerk_ref_clerk_auth_config", "target": "workos_authkit_ref_workos_jwt", "relation": "semantically_similar_to", "confidence": "INFERRED", "confidence_score": 0.85, "source_file": ".agents/skills/convex-setup-auth/references/clerk.md", "source_location": null, "weight": 1.0}, {"source": "clerk_ref_convex_provider_with_clerk", "target": "auth0_ref_convex_provider_with_auth0", "relation": "semantically_similar_to", "confidence": "INFERRED", "confidence_score": 0.95, "source_file": ".agents/skills/convex-setup-auth/references/clerk.md", "source_location": null, "weight": 1.0}, {"source": "convex_auth_pattern_jwt_validation", "target": "auth0_ref_convex_auth_config", "relation": "rationale_for", "confidence": "INFERRED", "confidence_score": 0.85, "source_file": ".agents/skills/convex-setup-auth/references/clerk.md", "source_location": null, "weight": 1.0}, {"source": "convex_auth_pattern_jwt_validation", "target": "clerk_ref_clerk_auth_config", "relation": "rationale_for", "confidence": "INFERRED", "confidence_score": 0.85, "source_file": ".agents/skills/convex-setup-auth/references/clerk.md", "source_location": null, "weight": 1.0}], "hyperedges": []}